parfum/__init__.py
parfum/anonymizer.py
parfum/chat.py
parfum/cli.py
parfum/detector.py
parfum/entities.py
parfum/patterns.py
parfum/strategies.py
parfum-0.1.0.dist-info/METADATA
parfum-0.1.0.dist-info/WHEEL
parfum-0.1.0.dist-info/entry_points.txt
parfum-0.1.0.dist-info/licenses/LICENSE
parfum-0.1.0.dist-info/RECORD
