Metadata-Version: 2.4
Name: parfum
Version: 0.1.0
Summary: Anonymize personal information in chat data for LLM training
Project-URL: Homepage, https://github.com/astroknot-sheep/parfum
Project-URL: Documentation, https://github.com/astroknot-sheep/parfum#readme
Project-URL: Repository, https://github.com/astroknot-sheep/parfum
Project-URL: Issues, https://github.com/astroknot-sheep/parfum/issues
Author-email: Dhriman <contact@dhrimandeka.com>
License-Expression: MIT
License-File: LICENSE
Keywords: anonymization,chat,data-cleaning,llm,machine-learning,nlp,pii,privacy
Classifier: Development Status :: 4 - Beta
Classifier: Intended Audience :: Developers
Classifier: Intended Audience :: Science/Research
Classifier: License :: OSI Approved :: MIT License
Classifier: Operating System :: OS Independent
Classifier: Programming Language :: Python :: 3
Classifier: Programming Language :: Python :: 3.9
Classifier: Programming Language :: Python :: 3.10
Classifier: Programming Language :: Python :: 3.11
Classifier: Programming Language :: Python :: 3.12
Classifier: Topic :: Scientific/Engineering :: Artificial Intelligence
Classifier: Topic :: Security
Classifier: Topic :: Text Processing
Requires-Python: >=3.9
Requires-Dist: faker>=18.0.0
Requires-Dist: regex>=2023.0.0
Provides-Extra: all
Requires-Dist: pytest-cov>=4.0.0; extra == 'all'
Requires-Dist: pytest>=7.0.0; extra == 'all'
Requires-Dist: spacy>=3.5.0; extra == 'all'
Provides-Extra: dev
Requires-Dist: pytest-cov>=4.0.0; extra == 'dev'
Requires-Dist: pytest>=7.0.0; extra == 'dev'
Provides-Extra: ner
Requires-Dist: spacy>=3.5.0; extra == 'ner'
